tests/__init__.py
tests/utils.py
tests/attributions/__init__.py
tests/attributions/test_callable.py
tests/attributions/test_common.py
tests/attributions/test_deconvnet.py
tests/attributions/test_forgrad.py
tests/attributions/test_grad_cam.py
tests/attributions/test_grad_cam_pp.py
tests/attributions/test_gradient_input.py
tests/attributions/test_guided_backprop.py
tests/attributions/test_hsic.py
tests/attributions/test_integrated_gradients.py
tests/attributions/test_kernel_shap.py
tests/attributions/test_lime.py
tests/attributions/test_object_detector.py
tests/attributions/test_occlusion.py
tests/attributions/test_online_statistics.py
tests/attributions/test_rise.py
tests/attributions/test_saliency.py
tests/attributions/test_smoothgrad.py
tests/attributions/test_sobol.py
tests/attributions/test_tabular_data.py
tests/commons/__init__.py
tests/commons/test_data_conversion.py
tests/commons/test_model_override.py
tests/commons/test_object_detection_operator.py
tests/commons/test_operators.py
tests/commons/test_operators_operations.py
tests/commons/test_segmentation_operator.py
tests/concepts/__init__.py
tests/concepts/test_cav.py
tests/concepts/test_craft_tf.py
tests/concepts/test_craft_torch.py
tests/concepts/test_tcav.py
tests/example_based/__init__.py
tests/example_based/test_cole.py
tests/example_based/test_contrastive.py
tests/example_based/test_datasets_harmonization.py
tests/example_based/test_kleor.py
tests/example_based/test_knn.py
tests/example_based/test_projections.py
tests/example_based/test_prototypes.py
tests/example_based/test_similar_examples.py
tests/example_based/test_tf_dataset_operation.py
tests/example_based/test_torch.py
tests/features_visualizations/__init__.py
tests/features_visualizations/test_losses.py
tests/features_visualizations/test_maco.py
tests/features_visualizations/test_objectives.py
tests/features_visualizations/test_optim.py
tests/features_visualizations/test_preconditionning.py
tests/features_visualizations/test_regularizers.py
Xplique-1.4.0.dist-info/LICENSE
Xplique-1.4.0.dist-info/METADATA
Xplique-1.4.0.dist-info/WHEEL
Xplique-1.4.0.dist-info/top_level.txt
Xplique-1.4.0.dist-info/RECORD
