Metadata-Version: 2.1
Name: Xplique
Version: 1.4.0
Summary: Explanations toolbox for Tensorflow 2
Author: Thomas FEL
Author-email: thomas_fel@brown.edu
License: MIT
Classifier: Development Status :: 4 - Beta
Classifier: License :: OSI Approved :: MIT License
Classifier: Programming Language :: Python
Classifier: Programming Language :: Python :: 3
Classifier: Operating System :: OS Independent
Requires-Python: >=3.6
License-File: LICENSE
Requires-Dist: numpy<2.0.0
Requires-Dist: tensorflow<2.16.0,>=2.1.0
Requires-Dist: scikit-learn
Requires-Dist: scikit-image
Requires-Dist: matplotlib
Requires-Dist: scipy
Requires-Dist: opencv-python
Requires-Dist: deprecated
Provides-Extra: docs
Requires-Dist: mkdocs; extra == "docs"
Requires-Dist: mkdocs-material; extra == "docs"
Requires-Dist: numkdoc; extra == "docs"
Provides-Extra: pytorch
Requires-Dist: torch; extra == "pytorch"
Provides-Extra: tests
Requires-Dist: pytest; extra == "tests"
Requires-Dist: pylint; extra == "tests"
